pysource_codegen/__about__.py
pysource_codegen/__init__.py
pysource_codegen/__main__.py
pysource_codegen/_codegen.py
pysource_codegen/_limits.py
pysource_codegen/_utils.py
pysource_codegen/ast_info.py
pysource_codegen/py.typed
pysource_codegen/static_type_info.py
pysource_codegen/types.py
pysource_codegen-0.7.1.dist-info/METADATA
pysource_codegen-0.7.1.dist-info/WHEEL
pysource_codegen-0.7.1.dist-info/entry_points.txt
pysource_codegen-0.7.1.dist-info/licenses/LICENSE
pysource_codegen-0.7.1.dist-info/RECORD
