Metadata-Version: 2.4
Name: pysource-codegen
Version: 0.7.1
Summary: generate random python code to test linter/formatter/and other tools
Project-URL: Documentation, https://github.com/15r10nk/pysource-codegen#readme
Project-URL: Issues, https://github.com/15r10nk/pysource-codegen/issues
Project-URL: Source, https://github.com/15r10nk/pysource-codegen
Author-email: Frank Hoffmann <15r10nk-git@polarbit.de>
License-Expression: MIT
License-File: LICENSE
Classifier: Development Status :: 4 - Beta
Classifier: License :: OSI Approved :: MIT License
Classifier: Programming Language :: Python
Classifier: Programming Language :: Python :: 3.8
Classifier: Programming Language :: Python :: 3.9
Classifier: Programming Language :: Python :: 3.10
Classifier: Programming Language :: Python :: 3.11
Classifier: Programming Language :: Python :: 3.12
Classifier: Programming Language :: Python :: 3.13
Classifier: Programming Language :: Python :: 3.14
Classifier: Programming Language :: Python :: Implementation :: CPython
Classifier: Programming Language :: Python :: Implementation :: PyPy
Requires-Python: >=3.8
Requires-Dist: astunparse>=1.6.3; python_version < '3.9'
Requires-Dist: typing-extensions>=4.7.1
